yta_audio_narration_common/__init__.py
yta_audio_narration_common/consts.py
yta_audio_narration_common/enums.py
yta_audio_narration_common/voice.py
yta_audio_narration_common-0.0.1.dist-info/LICENSE
yta_audio_narration_common-0.0.1.dist-info/METADATA
yta_audio_narration_common-0.0.1.dist-info/WHEEL
yta_audio_narration_common-0.0.1.dist-info/RECORD
