Metadata-Version: 2.3
Name: yta-audio-narration-common
Version: 0.0.1
Summary: Youtube Autonomous Audio Narration Common Module.
Author: danialcala94
Author-email: danielalcalavalera@gmail.com
Requires-Python: ==3.9
Classifier: Programming Language :: Python :: 3
Classifier: Programming Language :: Python :: 3.9
Requires-Dist: yta_constants (>=0.0.1,<1.0.0)
